{
  "stamp": "2026-06-04",
  "items": [
    {
      "placeId": "ChIJqWvgD-yNpzERS66-PApwcs0",
      "placeName": "Bún Quậy Bạch Đằng",
      "mode": "photo",
      "photoPaths": [
        "out/media/2026-06-04-RS66-PApwcs0-0.jpg",
        "out/media/2026-06-04-RS66-PApwcs0-1.jpg",
        "out/media/2026-06-04-RS66-PApwcs0-2.jpg",
        "out/media/2026-06-04-RS66-PApwcs0-3.jpg",
        "out/media/2026-06-04-RS66-PApwcs0-4.jpg",
        "out/media/2026-06-04-RS66-PApwcs0-5.jpg",
        "out/media/2026-06-04-RS66-PApwcs0-6.jpg",
        "out/media/2026-06-04-RS66-PApwcs0-7.jpg"
      ],
      "videoPath": null,
      "content": {
        "hookArchetype": "POV_REVEAL",
        "facebook": {
          "caption": "POV: you finally found the good Bún Quậy in Phu Quoc.\n\nBún Quậy Bạch Đằng on 32A Đường Bạch Đằng is pulling a 4.9 from 203 reviews. That number is almost impossible for a local noodle spot. The broth is the reason. Locals have been eating here for years while tourists walk straight past.\n\nIf you're skipping the resort breakfast for one meal, make it this one.\n\nSave this for your Phu Quoc trip.",
          "video_caption": "Slurping Bún Quậy at the spot locals actually rate. 4.9 stars. 203 reviews. Bún Quậy Bạch Đằng on Đường Bạch Đằng. This bowl is why you eat local in Phu Quoc.",
          "first_comment": "#PhuQuoc #PhuQuocFood #BunQuay #VisitVietnam #TravelTips #PhuQuocRestaurants #VietnamFood"
        },
        "instagram": {
          "caption": "POV: you found the good Bún Quậy. 4.9 stars. 203 reviews. Bún Quậy Bạch Đằng delivers.\n\nTag your travel buddy.",
          "video_caption": "4.9 stars at a local noodle spot. Bún Quậy Bạch Đằng is the bowl tourists keep missing.",
          "hashtags": "#PhuQuocFood #PhuQuocTips #BunQuay #VietnamTravel #TravelTips #TravelReels #PhuQuoc #VietnamFood #LocalEats"
        },
        "tiktok": {
          "caption": "4.9 stars. This bowl at Bún Quậy Bạch Đằng is why you eat local in Phu Quoc. #PhuQuoc #PhuQuocFood #VietnamTravel #BunQuay"
        },
        "video_script": {
          "hook": "4.9 STARS. LOCAL NOODLE SPOT.",
          "scenes": [
            "Arrive at 32A Đường Bạch Đằng, street-level signage",
            "Close-up: broth poured into bowl",
            "Noodles lifted with chopsticks, steam rising",
            "Packed tables, mostly local diners",
            "Phone screen showing 4.9 rating, 203 reviews"
          ],
          "cta": "Save this for your Phu Quoc trip."
        }
      }
    },
    {
      "placeId": "ChIJccUCppGNpzERY4DpGOmVA7o",
      "placeName": "Phở Hòa",
      "mode": "video",
      "photoPaths": [
        "out/media/2026-06-04-RY4DpGOmVA7o-0.jpg",
        "out/media/2026-06-04-RY4DpGOmVA7o-1.jpg",
        "out/media/2026-06-04-RY4DpGOmVA7o-2.jpg",
        "out/media/2026-06-04-RY4DpGOmVA7o-3.jpg",
        "out/media/2026-06-04-RY4DpGOmVA7o-4.jpg",
        "out/media/2026-06-04-RY4DpGOmVA7o-5.jpg",
        "out/media/2026-06-04-RY4DpGOmVA7o-6.jpg",
        "out/media/2026-06-04-RY4DpGOmVA7o-7.jpg"
      ],
      "videoPath": "out/media/2026-06-04-RY4DpGOmVA7o.mp4",
      "content": {
        "hookArchetype": "NUMBER_REVEAL",
        "facebook": {
          "caption": "4.8 stars. 857 reviews. One bowl of phở on Đường Trần Hưng Đạo.\n\nPhở Hòa keeps showing up on locals' lists and it earns every star. The broth hits different when you're eating where the neighborhood actually eats, not where the resort pointed you.\n\nPhu Quoc has no shortage of tourist traps. This isn't one of them.\n\n📍 128D Đường Trần Hưng Đạo, Khu phố 7\n\nSave this for your Phu Quoc trip.",
          "video_caption": "Watch the steam rise off a bowl at Phở Hòa. 857 people rated this 4.8 stars. The spoon tells you why in the first sip. 📍 128D Đường Trần Hưng Đạo, Phú Quốc.",
          "first_comment": "#PhuQuoc #PhuQuocFood #PhuQuocRestaurants #VisitVietnam #VietnamFood #TravelTips #PhuQuocTips"
        },
        "instagram": {
          "caption": "4.8 stars. 857 reviews. One address: Phở Hòa.\n\nLocals eat here. The broth proves why.\n\n📍 128D Đường Trần Hưng Đạo, Phú Quốc. Save this.",
          "video_caption": "First spoonful at Phở Hòa and you get it immediately. 4.8 stars, 857 reviews. Phu Quoc's bowl to beat. 📍",
          "hashtags": "#PhuQuocFood #PhuQuocRestaurants #PhuQuocTips #VietnamFood #VietnamTravel #TravelTips #TravelReels #Pho"
        },
        "tiktok": {
          "caption": "4.8 stars. 857 reviews. This bowl at Phở Hòa earns both. #PhuQuoc #PhuQuocFood #VietnamFood #Pho #TravelTips"
        },
        "video_script": {
          "hook": "4.8★ 857 reviews. One bowl.",
          "scenes": [
            "Close-up: broth poured into bowl",
            "Steam rising, slow zoom out",
            "Hands add herbs and chili",
            "First spoonful lifted to camera",
            "Packed tables, locals eating",
            "Sign: Phở Hòa, Trần Hưng Đạo"
          ],
          "cta": "Save this for your Phu Quoc trip."
        }
      }
    },
    {
      "placeId": "ChIJt-QpkieNpzEROHxvKTl08as",
      "placeName": "Xóm Mới Garden Phú Quốc 씀모이가든 푸꾸옥 맛집",
      "mode": "photo",
      "photoPaths": [
        "out/media/2026-06-04-ROHxvKTl08as-0.jpg",
        "out/media/2026-06-04-ROHxvKTl08as-1.jpg",
        "out/media/2026-06-04-ROHxvKTl08as-2.jpg",
        "out/media/2026-06-04-ROHxvKTl08as-3.jpg",
        "out/media/2026-06-04-ROHxvKTl08as-4.jpg",
        "out/media/2026-06-04-ROHxvKTl08as-5.jpg",
        "out/media/2026-06-04-ROHxvKTl08as-6.jpg",
        "out/media/2026-06-04-ROHxvKTl08as-7.jpg"
      ],
      "videoPath": null,
      "content": {
        "hookArchetype": "NUMBER_REVEAL",
        "facebook": {
          "caption": "4.9 stars. 2,114 reviews. At a garden restaurant on Trần Hưng Đạo.\n\nXóm Mới Garden Phú Quốc 씀모이가든 푸꾸옥 맛집 is not flying under the radar anymore, but the food still hits like it is. Vietnamese home cooking, open-air garden setting, the kind of place locals and return visitors both claim as their own.\n\nFind it at 114 Đường Trần Hưng Đạo, Khu Phố 7. Save this for your Phu Quoc trip.",
          "video_caption": "Plates landing on garden tables. A 4.9-star Vietnamese restaurant in Phu Quoc, 2,114 people rated it. Watch what they keep ordering at Xóm Mới Garden Phú Quốc 씀모이가든 푸꾸옥 맛집.",
          "first_comment": "#PhuQuoc #PhuQuocFood #PhuQuocRestaurants #VisitVietnam #VietnamFood #TravelTips #PhuQuocTips"
        },
        "instagram": {
          "caption": "4.9 stars. 2,114 reviews. One garden restaurant in Phu Quoc.\n\nXóm Mới Garden Phú Quốc 씀모이가든 푸꾸옥 맛집 earns every one. Tag your travel buddy.",
          "video_caption": "2,114 people rated this Phu Quoc garden restaurant 4.9 stars. See why at Xóm Mới Garden Phú Quốc 씀모이가든 푸꾸옥 맛집.",
          "hashtags": "#PhuQuocFood #PhuQuocRestaurants #PhuQuocTips #VietnamTravel #VietnamFood #TravelReels #TravelTips"
        },
        "tiktok": {
          "caption": "4.9 stars, 2,114 reviews. Xóm Mới Garden Phú Quốc 씀모이가든 is the real deal. #PhuQuoc #PhuQuocFood #VietnamTravel #TravelTips"
        },
        "video_script": {
          "hook": "4.9★, 2,114 reviews. In Phu Quoc.",
          "scenes": [
            "Arrive at open-air garden entrance",
            "Pan across packed tables, locals dining",
            "Close-up: steaming Vietnamese dishes served",
            "Reaction shot: first bite, eyes wide",
            "Show 4.9-star rating on screen"
          ],
          "cta": "Save this for your Phu Quoc trip."
        }
      }
    },
    {
      "placeId": "ChIJ67MzfTqNpzERl5vEmwYkACQ",
      "placeName": "Phở Lý Quốc Sư",
      "mode": "video",
      "photoPaths": [
        "out/media/2026-06-04-Rl5vEmwYkACQ-0.jpg",
        "out/media/2026-06-04-Rl5vEmwYkACQ-1.jpg",
        "out/media/2026-06-04-Rl5vEmwYkACQ-2.jpg",
        "out/media/2026-06-04-Rl5vEmwYkACQ-3.jpg",
        "out/media/2026-06-04-Rl5vEmwYkACQ-4.jpg",
        "out/media/2026-06-04-Rl5vEmwYkACQ-5.jpg",
        "out/media/2026-06-04-Rl5vEmwYkACQ-6.jpg",
        "out/media/2026-06-04-Rl5vEmwYkACQ-7.jpg"
      ],
      "videoPath": "out/media/2026-06-04-Rl5vEmwYkACQ.mp4",
      "content": {
        "hookArchetype": "POV_REVEAL",
        "facebook": {
          "caption": "POV: you skipped the tourist pho spots and ended up at Phở Lý Quốc Sư on Đ. 30 Tháng 4. 4.6 stars. 486 reviews. Bowl in hand before the crowds arrive. This is the kind of local pho stop that makes you reset your whole Phu Quoc itinerary. Save this for your Phu Quoc trip.",
          "video_caption": "Steam rising. Bowl hits the table. 486 locals and travelers rated Phở Lý Quốc Sư 4.6 stars and it shows. This is your morning sorted on Phu Quoc.",
          "first_comment": "#PhuQuoc #PhuQuocFood #PhuQuocRestaurants #VisitVietnam #TravelTips"
        },
        "instagram": {
          "caption": "POV: found the pho spot locals actually rate. Phở Lý Quốc Sư. 4.6★, 486 reviews. Go early. Save this for your Phu Quoc trip.",
          "video_caption": "4.6 stars. 486 reviews. Phở Lý Quốc Sư delivers every single morning. Don't sleep on it.",
          "hashtags": "#PhuQuocFood #PhuQuocRestaurants #PhuQuocTips #VietnamTravel #TravelTips #TravelReels #FoodInVietnam"
        },
        "tiktok": {
          "caption": "The pho bowl Phu Quoc locals keep going back to. Phở Lý Quốc Sư, 4.6★ 486 reviews. #PhuQuoc #PhuQuocFood #VietnamFood #TravelTips"
        },
        "video_script": {
          "hook": "4.6★ pho. Locals keep coming back.",
          "scenes": [
            "Close-up: broth poured into bowl",
            "Hands adding herbs and lime",
            "Wide shot of busy local tables",
            "Steam rising in morning light",
            "Spoon lifts noodles, slow motion"
          ],
          "cta": "Save this for your Phu Quoc trip."
        }
      }
    },
    {
      "placeId": "ChIJQf0ZjIeNpzERtMMtf7OdVyg",
      "placeName": "Mì Tê Lý Thường Kiệt - Artisan Noodles",
      "mode": "photo",
      "photoPaths": [
        "out/media/2026-06-04-RtMMtf7OdVyg-0.jpg",
        "out/media/2026-06-04-RtMMtf7OdVyg-1.jpg",
        "out/media/2026-06-04-RtMMtf7OdVyg-2.jpg",
        "out/media/2026-06-04-RtMMtf7OdVyg-3.jpg",
        "out/media/2026-06-04-RtMMtf7OdVyg-4.jpg",
        "out/media/2026-06-04-RtMMtf7OdVyg-5.jpg",
        "out/media/2026-06-04-RtMMtf7OdVyg-6.jpg",
        "out/media/2026-06-04-RtMMtf7OdVyg-7.jpg"
      ],
      "videoPath": null,
      "content": {
        "hookArchetype": "POV_REVEAL",
        "facebook": {
          "caption": "POV: you ducked into a side street on Lý Thường Kiệt and found Mì Tê Lý Thường Kiệt. Artisan noodles, 4.6 stars, 160 reviews deep. This is not a tourist trap. This is the real bowl locals come back for. Small shop, serious craft, the kind of place you walk past once and regret. Don't walk past twice. Save this for your Phu Quoc trip.",
          "video_caption": "Pulling up to 58B Lý Thường Kiệt for a bowl at Mì Tê Lý Thường Kiệt. 4.6 stars from 160 reviewers and the line tells you everything. Watch the noodles hit the bowl. You'll understand.",
          "first_comment": "#PhuQuoc #PhuQuocFood #PhuQuocNoodles #VisitVietnam #TravelTips"
        },
        "instagram": {
          "caption": "Took a wrong turn on Lý Thường Kiệt. Found Mì Tê Lý Thường Kiệt. 4.6 stars. Don't walk past this one. Tag your travel buddy.",
          "video_caption": "Bowl landing at Mì Tê Lý Thường Kiệt. 4.6 stars. Artisan noodles on a Phu Quoc side street. This is the one.",
          "hashtags": "#PhuQuocFood #PhuQuocNoodles #PhuQuocTips #VietnamTravel #TravelTips #TravelReels #PhuQuoc"
        },
        "tiktok": {
          "caption": "Wrong turn. Best bowl. Mì Tê Lý Thường Kiệt hits 4.6 stars for a reason. #PhuQuoc #PhuQuocFood #PhuQuocTips #VietnamTravel"
        },
        "video_script": {
          "hook": "Walked past this. Big mistake.",
          "scenes": [
            "Street sign: 58B Lý Thường Kiệt zooms in",
            "Push through narrow shop entrance",
            "Chef pulls fresh noodle strands",
            "Broth poured over noodles, steam rising",
            "Close-up: chopsticks lift first bite",
            "Screen text: 4.6 stars, 160 reviews"
          ],
          "cta": "Save this for your Phu Quoc trip."
        }
      }
    },
    {
      "placeId": "ChIJR1rvyAmNpzERHEdIhXDMsII",
      "placeName": "Bún Quậy Kiến-Xây | Local PhuQuoc Seafood Noodles",
      "mode": "video",
      "photoPaths": [
        "out/media/2026-06-04-RHEdIhXDMsII-0.jpg",
        "out/media/2026-06-04-RHEdIhXDMsII-1.jpg",
        "out/media/2026-06-04-RHEdIhXDMsII-2.jpg",
        "out/media/2026-06-04-RHEdIhXDMsII-3.jpg",
        "out/media/2026-06-04-RHEdIhXDMsII-4.jpg",
        "out/media/2026-06-04-RHEdIhXDMsII-5.jpg",
        "out/media/2026-06-04-RHEdIhXDMsII-6.jpg",
        "out/media/2026-06-04-RHEdIhXDMsII-7.jpg"
      ],
      "videoPath": "out/media/2026-06-04-RHEdIhXDMsII.mp4",
      "content": {
        "hookArchetype": "LOCALS_DONT_TELL",
        "facebook": {
          "caption": "Tourists keep walking past this one. Bún Quậy Kiến-Xây on Đường Trần Hưng Đạo is where Phu Quoc locals actually eat their noodles. Bún Quậy is the island's own dish: springy hand-rolled noodles, fresh seafood, light broth. 2,574 reviews and somehow still off most itineraries. Get here early. Bowls go fast. Save this for your Phu Quoc trip.",
          "video_caption": "Watch the noodles hit the bowl at Bún Quậy Kiến-Xây. Fresh seafood, local broth, 2,574 people rated it 4.2 stars. Still not on the tourist map. Now you know.",
          "first_comment": "#PhuQuoc #PhuQuocFood #PhuQuocNoodles #VisitVietnam #TravelTips #LocalFood #PhuQuocTravel"
        },
        "instagram": {
          "caption": "Locals eat here. Tourists don't know it exists. Bún Quậy Kiến-Xây, Phu Quoc's own noodle dish, 2,574 reviews. Save this.",
          "video_caption": "Bowl of Bún Quậy Kiến-Xây incoming. This is what Phu Quoc locals actually order. 4.2 stars, zero tourist crowds.",
          "hashtags": "#PhuQuocFood #PhuQuocNoodles #PhuQuocTips #VietnamTravel #TravelTips #TravelReels #LocalEats #PhuQuoc #VietnamFood #ThingsToDoPhuQuoc"
        },
        "tiktok": {
          "caption": "The noodle shop Phu Quoc tourists walk past every day. Bún Quậy Kiến-Xây. 2,574 reviews. Go. #PhuQuoc #PhuQuocFood #LocalEats #VietnamTravel #TravelTips"
        },
        "video_script": {
          "hook": "Locals don't post about this.",
          "scenes": [
            "Exterior shot: busy local crowd, no tourists",
            "Chef rolls fresh bún quậy noodles by hand",
            "Seafood dropped into steaming broth",
            "Bowl lands on table, close-up pour",
            "First bite reaction, no words needed"
          ],
          "cta": "Save this for your Phu Quoc trip."
        }
      }
    },
    {
      "placeId": "ChIJOawITM2NpzERxPm19sYAUpo",
      "placeName": "Phở bò Nam Định",
      "mode": "photo",
      "photoPaths": [
        "out/media/2026-06-04-RxPm19sYAUpo-0.jpg",
        "out/media/2026-06-04-RxPm19sYAUpo-1.jpg",
        "out/media/2026-06-04-RxPm19sYAUpo-2.jpg",
        "out/media/2026-06-04-RxPm19sYAUpo-3.jpg",
        "out/media/2026-06-04-RxPm19sYAUpo-4.jpg",
        "out/media/2026-06-04-RxPm19sYAUpo-5.jpg",
        "out/media/2026-06-04-RxPm19sYAUpo-6.jpg",
        "out/media/2026-06-04-RxPm19sYAUpo-7.jpg"
      ],
      "videoPath": null,
      "content": {
        "hookArchetype": "NUMBER_REVEAL",
        "facebook": {
          "caption": "751 reviews. 4.6 stars. Under $10 a bowl.\n\nPhở bò Nam Định on Đường Trần Hưng Đạo is not a tourist restaurant. It's where locals eat pho before 8am and the broth runs out by noon.\n\nNam Định-style means cleaner, lighter broth than the south. Beef is sliced thin. Noodles are firm. No fuss.\n\nGet there early. Save this for your Phu Quoc trip.",
          "video_caption": "Watch the broth hit the bowl. That's Nam Định-style pho, under $10, 4.6 stars from 751 real reviews. Đường Trần Hưng Đạo. Go before noon or go hungry.",
          "first_comment": "#PhuQuoc #PhuQuocFood #PhuQuocRestaurants #VisitVietnam #TravelTips"
        },
        "instagram": {
          "caption": "751 reviews. 4.6 stars. Under $10 a bowl.\n\nPhở bò Nam Định. Broth runs out by noon. Go early.\n\nSave this for your Phu Quoc trip.",
          "video_caption": "Broth hits different at 7am. Phở bò Nam Định, 4.6 stars, under $10. Don't sleep in.",
          "hashtags": "#PhuQuocFood #PhuQuocRestaurants #PhuQuocTips #VietnamTravel #TravelTips #TravelReels #Pho"
        },
        "tiktok": {
          "caption": "751 reviews don't lie. Best pho under $10 in Phu Quoc. #PhuQuoc #PhuQuocFood #VietnamFood #Pho"
        },
        "video_script": {
          "hook": "751 reviews. Under $10.",
          "scenes": [
            "Close-up: ladle pours hot broth into bowl",
            "Thin beef slices dropped in, steam rising",
            "Tight shot: firm noodles lifted with chopsticks",
            "Wide shot: packed local crowd, simple plastic stools",
            "Text overlay: Đường Trần Hưng Đạo, 4.6 stars"
          ],
          "cta": "Save this for your Phu Quoc trip."
        }
      }
    },
    {
      "placeId": "ChIJS797XwCNpzERpdvvoNGRBK4",
      "placeName": "Phở Vương Phú Quốc",
      "mode": "video",
      "photoPaths": [
        "out/media/2026-06-04-RpdvvoNGRBK4-0.jpg",
        "out/media/2026-06-04-RpdvvoNGRBK4-1.jpg",
        "out/media/2026-06-04-RpdvvoNGRBK4-2.jpg",
        "out/media/2026-06-04-RpdvvoNGRBK4-3.jpg",
        "out/media/2026-06-04-RpdvvoNGRBK4-4.jpg",
        "out/media/2026-06-04-RpdvvoNGRBK4-5.jpg",
        "out/media/2026-06-04-RpdvvoNGRBK4-6.jpg",
        "out/media/2026-06-04-RpdvvoNGRBK4-7.jpg"
      ],
      "videoPath": "out/media/2026-06-04-RpdvvoNGRBK4.mp4",
      "content": {
        "hookArchetype": "NUMBER_REVEAL",
        "facebook": {
          "caption": "4.9 stars. 244 reviews. One bowl of pho in Phu Quoc.\n\nPhở Vương Phú Quốc sits at 70 Đ. 30 Tháng 4 and the locals keep coming back. Rich broth, real depth, the kind of bowl that makes you order a second before you finish the first.\n\nNot a resort restaurant. Not a tourist trap. Just pho done right.\n\nSave this for your Phu Quoc trip.",
          "video_caption": "Watch that broth hit the bowl. Phở Vương Phú Quốc, 4.9 stars, 244 reviews. This is what locals eat for breakfast on the island. Address in bio.",
          "first_comment": "#PhuQuoc #PhuQuocFood #PhuQuocRestaurants #VisitVietnam #TravelTips"
        },
        "instagram": {
          "caption": "4.9 stars. 244 reviews. One bowl at Phở Vương Phú Quốc.\n\nBroth this deep takes hours. Worth every minute.\n\nSave this for your Phu Quoc trip.",
          "video_caption": "Locals line up. 4.9 stars. Phở Vương Phú Quốc delivers every time. Don't skip breakfast on the island.",
          "hashtags": "#PhuQuocFood #PhuQuocRestaurants #PhuQuocTips #VietnamTravel #TravelTips #TravelReels #PhoVietnam"
        },
        "tiktok": {
          "caption": "4.9 stars in Phu Quoc. This bowl of pho hits different. #PhuQuoc #PhuQuocFood #VietnamTravel #PhoVietnam"
        },
        "video_script": {
          "hook": "4.9 stars. 244 reviews.",
          "scenes": [
            "Close-up: steaming broth poured into bowl",
            "Hands pulling apart fresh herbs and bean sprouts",
            "Chopsticks lift thick rice noodles",
            "Wide shot: packed local tables, no tourists",
            "Final frame: storefront at 70 Đ. 30 Tháng 4"
          ],
          "cta": "Save this for your Phu Quoc trip."
        }
      }
    },
    {
      "placeId": "ChIJyyzkOQCNpzERhV6CqtU5LxQ",
      "placeName": "Phở Chào",
      "mode": "photo",
      "photoPaths": [
        "out/media/2026-06-04-RhV6CqtU5LxQ-0.jpg",
        "out/media/2026-06-04-RhV6CqtU5LxQ-1.jpg",
        "out/media/2026-06-04-RhV6CqtU5LxQ-2.jpg",
        "out/media/2026-06-04-RhV6CqtU5LxQ-3.jpg",
        "out/media/2026-06-04-RhV6CqtU5LxQ-4.jpg",
        "out/media/2026-06-04-RhV6CqtU5LxQ-5.jpg",
        "out/media/2026-06-04-RhV6CqtU5LxQ-6.jpg",
        "out/media/2026-06-04-RhV6CqtU5LxQ-7.jpg"
      ],
      "videoPath": null,
      "content": {
        "hookArchetype": "POV_REVEAL",
        "facebook": {
          "caption": "POV: you're walking Trần Hưng Đạo and you almost skip Phở Chào. Don't be that person.\n\n4.8 stars. 93 reviews. A bowl of phở on a street lined with tourist traps. This one locals actually back.\n\nFind it at 127/2 Đường Trần Hưng Đạo, Khu phố 7. Show up hungry.\n\nSave this for your Phu Quoc trip.",
          "video_caption": "Steam rising. Bowl lands on the table. 4.8 stars on Trần Hưng Đạo and most tourists walk straight past Phở Chào. Not anymore.",
          "first_comment": "#PhuQuoc #PhuQuocFood #PhuQuocRestaurants #VisitVietnam #TravelTips"
        },
        "instagram": {
          "caption": "POV: you almost walked past the 4.8-star phở spot on Trần Hưng Đạo. Phở Chào. Remember the name.\n\nTag your travel buddy.",
          "video_caption": "Hot bowl. 4.8 stars. Phở Chào keeps getting overlooked. Not after this.",
          "hashtags": "#PhuQuocFood #PhuQuocRestaurants #PhuQuocTips #VietnamTravel #TravelTips #TravelReels #Pho"
        },
        "tiktok": {
          "caption": "Almost missed this 4.8-star phở spot in Phu Quoc. Phở Chào on Trần Hưng Đạo. Go. #PhuQuoc #PhuQuocFood #VietnamTravel"
        },
        "video_script": {
          "hook": "POV: you almost skipped this.",
          "scenes": [
            "Walk along busy Trần Hưng Đạo",
            "Stop at Phở Chào sign, 127/2",
            "Close-up: steaming bowl hits table",
            "Slow pour of broth, herbs dropped in",
            "Phone shows 4.8 stars, 93 reviews"
          ],
          "cta": "Save this for your Phu Quoc trip."
        }
      }
    },
    {
      "placeId": "ChIJc9uFHgCNpzERe-wLYlkuV_Q",
      "placeName": "Phở bát đá -bún bò bát đá Anh Đạt",
      "mode": "video",
      "photoPaths": [
        "out/media/2026-06-04-Re-wLYlkuV_Q-0.jpg",
        "out/media/2026-06-04-Re-wLYlkuV_Q-1.jpg",
        "out/media/2026-06-04-Re-wLYlkuV_Q-2.jpg",
        "out/media/2026-06-04-Re-wLYlkuV_Q-3.jpg",
        "out/media/2026-06-04-Re-wLYlkuV_Q-4.jpg",
        "out/media/2026-06-04-Re-wLYlkuV_Q-5.jpg",
        "out/media/2026-06-04-Re-wLYlkuV_Q-6.jpg",
        "out/media/2026-06-04-Re-wLYlkuV_Q-7.jpg"
      ],
      "videoPath": "out/media/2026-06-04-Re-wLYlkuV_Q.mp4",
      "content": {
        "hookArchetype": "NUMBER_REVEAL",
        "facebook": {
          "caption": "4.8 stars. 62 reviews. One of the best-rated pho spots on the island. Phở bát đá -bún bò bát đá Anh Đạt on 12 Lê Lợi serves pho and bun bo in a stone bowl, keeping it hot from first bite to last. No frills. No tourist markup. Just a bowl that earns those stars. Save this for your Phu Quoc trip.",
          "video_caption": "Stone bowl hits the table still bubbling. Phở bát đá Anh Đạt, 4.8 stars, and a line of locals who know exactly why. Watch until the end.",
          "first_comment": "#PhuQuoc #PhuQuocFood #PhuQuocRestaurants #VisitVietnam #TravelTips"
        },
        "instagram": {
          "caption": "4.8 stars. 62 reviews. Stone bowl pho that stays hot to the last bite. Phở bát đá Anh Đạt, 12 Lê Lợi. Save this.",
          "video_caption": "Stone bowl arrives still boiling. 4.8 stars at Phở bát đá Anh Đạt. Locals eat here daily.",
          "hashtags": "#PhuQuocFood #PhuQuocRestaurants #PhuQuocTips #VietnamTravel #TravelTips #TravelReels #PhuQuoc"
        },
        "tiktok": {
          "caption": "4.8 stars on a stone bowl pho spot locals actually go to. Phở bát đá Anh Đạt, Phu Quoc. 📍 #PhuQuoc #PhuQuocFood #VietnamEats #TravelTips"
        },
        "video_script": {
          "hook": "4.8 stars. 62 locals can't lie.",
          "scenes": [
            "Stone bowl lands on table, steam rising",
            "Close-up: broth still bubbling at the rim",
            "Chopsticks pulling thick bun bo noodles",
            "Wide shot: packed local dining room",
            "Rating card: 4.8★, 12 Lê Lợi, Phu Quoc"
          ],
          "cta": "Save this for your Phu Quoc trip."
        }
      }
    },
    {
      "placeId": "ChIJP-wbXH2MpzERblHYWN8k8pk",
      "placeName": "Pho Sai Gon",
      "mode": "photo",
      "photoPaths": [
        "out/media/2026-06-04-RblHYWN8k8pk-0.jpg",
        "out/media/2026-06-04-RblHYWN8k8pk-1.jpg",
        "out/media/2026-06-04-RblHYWN8k8pk-2.jpg",
        "out/media/2026-06-04-RblHYWN8k8pk-3.jpg",
        "out/media/2026-06-04-RblHYWN8k8pk-4.jpg",
        "out/media/2026-06-04-RblHYWN8k8pk-5.jpg",
        "out/media/2026-06-04-RblHYWN8k8pk-6.jpg",
        "out/media/2026-06-04-RblHYWN8k8pk-7.jpg"
      ],
      "videoPath": null,
      "content": {
        "hookArchetype": "NUMBER_REVEAL",
        "facebook": {
          "caption": "4.5 stars. 567 reviews. One bowl of pho. Pho Sai Gon on Đ. 30 Tháng 4 keeps showing up on locals' lists for a reason. No frills, no tourist markup. Just broth that earns its reputation review after review. If you're in Khu 1 and need a real meal, this is the address. Save this for your Phu Quoc trip.",
          "video_caption": "Watch the bowl land on the table. Steam rising, broth clear, herbs piled high. This is what 567 reviewers kept coming back for at Pho Sai Gon. Real pho in Phu Quoc.",
          "first_comment": "#PhuQuoc #PhuQuocFood #PhuQuocRestaurants #VisitVietnam #TravelTips"
        },
        "instagram": {
          "caption": "4.5 stars. 567 reviews. One address: Pho Sai Gon, Đ. 30 Tháng 4. That broth doesn't lie. Tag your travel buddy.",
          "video_caption": "Bowl hits the table. Steam everywhere. 567 people already know about Pho Sai Gon. Now you do too.",
          "hashtags": "#PhuQuocFood #PhuQuocRestaurants #PhuQuocTips #VietnamTravel #TravelTips #TravelReels #PhuQuoc"
        },
        "tiktok": {
          "caption": "4.5 stars, 567 reviews, one bowl of pho. Pho Sai Gon delivers. #PhuQuoc #PhuQuocFood #VietnamTravel"
        },
        "video_script": {
          "hook": "4.5★ · 567 reviews · one bowl",
          "scenes": [
            "Exterior shot: street sign Đ. 30 Tháng 4",
            "Close-up: broth poured into bowl",
            "Steam rising in slow motion",
            "Herbs and beef added to bowl",
            "First spoonful lifted to camera",
            "Review count on screen: 567"
          ],
          "cta": "Save this for your Phu Quoc trip."
        }
      }
    },
    {
      "placeId": "ChIJjwOhDFuNpzERHGC-KN7pjUk",
      "placeName": "Thường Lạc Artisan Dumplings - Phú Quốc",
      "mode": "video",
      "photoPaths": [
        "out/media/2026-06-04-RHGC-KN7pjUk-0.jpg",
        "out/media/2026-06-04-RHGC-KN7pjUk-1.jpg",
        "out/media/2026-06-04-RHGC-KN7pjUk-2.jpg",
        "out/media/2026-06-04-RHGC-KN7pjUk-3.jpg",
        "out/media/2026-06-04-RHGC-KN7pjUk-4.jpg",
        "out/media/2026-06-04-RHGC-KN7pjUk-5.jpg",
        "out/media/2026-06-04-RHGC-KN7pjUk-6.jpg",
        "out/media/2026-06-04-RHGC-KN7pjUk-7.jpg"
      ],
      "videoPath": "out/media/2026-06-04-RHGC-KN7pjUk.mp4",
      "content": {
        "hookArchetype": "NUMBER_REVEAL",
        "facebook": {
          "caption": "514 reviews. 4.5 stars. For dumplings on a beach island.\n\nThường Lạc Artisan Dumplings in Phú Quốc is earning those numbers one fold at a time. Handcrafted dumplings, a Chinese kitchen doing the work, and a crowd that keeps coming back.\n\nNot every good meal in Phu Quoc is on the beach. Some of them are on Đ. 30 Tháng 4 and worth every detour.\n\nSave this for your Phu Quoc trip.",
          "video_caption": "Watch the folds. Thường Lạc Artisan Dumplings in Phú Quốc has 514 reviews at 4.5 stars and the dumplings will tell you why. This one earns its spot on your food list.",
          "first_comment": "#PhuQuoc #PhuQuocFood #PhuQuocRestaurants #VisitVietnam #TravelTips"
        },
        "instagram": {
          "caption": "514 reviews. 4.5 stars. For dumplings in Phu Quoc.\n\nThường Lạc Artisan Dumplings on Đ. 30 Tháng 4 is the detour worth taking. Save this.",
          "video_caption": "Handcrafted dumplings, 514 reviews, 4.5 stars. Thường Lạc in Phú Quốc is not messing around.",
          "hashtags": "#PhuQuocFood #PhuQuocRestaurants #PhuQuocTips #VietnamTravel #TravelTips #TravelReels #FoodInVietnam"
        },
        "tiktok": {
          "caption": "514 reviews for dumplings in Phu Quoc. Thường Lạc Artisan Dumplings is the real deal. #PhuQuoc #PhuQuocFood #VietnamTravel"
        },
        "video_script": {
          "hook": "514 reviews. Dumplings. Phu Quoc.",
          "scenes": [
            "Close-up: dumpling folds being pinched",
            "Steam rising from bamboo basket",
            "Full plate lands on table",
            "First bite, pull apart shot",
            "Street sign: Đ. 30 Tháng 4"
          ],
          "cta": "Save this for your Phu Quoc trip."
        }
      }
    }
  ]
}